{"personas": [{"nombre": "Dejah Thoris", "email": "dejah@email"}, {"nombre": "John", "email": "john@email"}, {"nombre": "Carthoris", "email": "carthoris@email"}, {"nombre": "aaa", "email": "aaa@email"}, {"nombre": "aaa", "email": "aaa@email"}, {"nombre": "aaa", "email": "aaa@email"}, {"nombre": "bbb", "email": "bbb@email"}, {"nombre": "bbb", "email": "bbb@email"}, {"nombre": "ccc", "email": "ccc@email"}, {"nombre": "ccc", "email": "ccc@email"}, {"nombre": "ccc", "email": "ccc@email"}], "direcciones": [{"direccion": "centro"}, {"direccion": "calle 13"}, {"direccion": "colonia sur"}, {"direccion": "colonia sur"}]}